pykml/__init__.py
pykml/factory.py
pykml/helpers.py
pykml/parser.py
pykml/util.py
pykml/schemas/atom-author-link.xsd
pykml/schemas/kml22gx.xsd
pykml/schemas/ogckml22.xsd
pykml/schemas/xAL.xsd
pykml/test/__init__.py
pykml/test/test_factory.py
pykml/test/test_helpers.py
pykml/test/test_parser.py
pykml/test/test_util.py
pykml/test/testfiles/simple_file_with_comments.kml
pykml/test/testfiles/google_kml_developers_guide/complete_tour_example.kml
pykml/test/testfiles/google_kml_tutorial/using_the_cdata_element.kml
pykml-0.2.0.dist-info/LICENSE.txt
pykml-0.2.0.dist-info/METADATA
pykml-0.2.0.dist-info/WHEEL
pykml-0.2.0.dist-info/entry_points.txt
pykml-0.2.0.dist-info/top_level.txt
pykml-0.2.0.dist-info/RECORD
